{
    "key": "group_5d1e8ef320d86",
    "title": "Default Page Template",
    "fields": [
        {
            "key": "field_5d1e8efc287f5",
            "label": "Content Blocks",
            "name": "content_blocks",
            "type": "flexible_content",
            "instructions": "",
            "required": 0,
            "conditional_logic": 0,
            "wrapper": {
                "width": "",
                "class": "",
                "id": ""
            },
            "layouts": {
                "5d1e8f198f830": {
                    "key": "5d1e8f198f830",
                    "name": "content_grid",
                    "label": "Content Grid",
                    "display": "block",
                    "sub_fields": [
                        {
                            "key": "field_5d1e8f35287f6",
                            "label": "Content Grid",
                            "name": "content_grid",
                            "type": "clone",
                            "instructions": "",
                            "required": 0,
                            "conditional_logic": 0,
                            "wrapper": {
                                "width": "",
                                "class": "",
                                "id": ""
                            },
                            "clone": [
                                "group_5d1af449d52eb"
                            ],
                            "display": "seamless",
                            "layout": "block",
                            "prefix_label": 0,
                            "prefix_name": 0
                        }
                    ],
                    "min": "",
                    "max": ""
                },
                "layout_5d262cee1ec68": {
                    "key": "layout_5d262cee1ec68",
                    "name": "food_menus_block",
                    "label": "Food Menus Block",
                    "display": "block",
                    "sub_fields": [
                        {
                            "key": "field_5d262d161ec69",
                            "label": "Food Menus Block",
                            "name": "food_menus_block",
                            "type": "clone",
                            "instructions": "",
                            "required": 0,
                            "conditional_logic": 0,
                            "wrapper": {
                                "width": "",
                                "class": "",
                                "id": ""
                            },
                            "clone": [
                                "group_5d262b0d522cc"
                            ],
                            "display": "seamless",
                            "layout": "block",
                            "prefix_label": 0,
                            "prefix_name": 0
                        }
                    ],
                    "min": "",
                    "max": ""
                }
            },
            "button_label": "Add Row",
            "min": "",
            "max": ""
        }
    ],
    "location": [
        [
            {
                "param": "post_type",
                "operator": "==",
                "value": "page"
            },
            {
                "param": "post_template",
                "operator": "==",
                "value": "default"
            }
        ]
    ],
    "menu_order": 0,
    "position": "normal",
    "style": "default",
    "label_placement": "top",
    "instruction_placement": "label",
    "hide_on_screen": [
        "the_content",
        "excerpt",
        "discussion",
        "comments",
        "revisions",
        "author",
        "format",
        "featured_image",
        "categories",
        "tags",
        "send-trackbacks"
    ],
    "active": 1,
    "description": "",
    "modified": 1562783143
}